[
  {
    "ParameterKey": "BitbucketSecret",
    "ParameterValue": ""
  },
  {
    "ParameterKey": "BitbucketServerUrl",
    "ParameterValue": "https://api.github.com/repos/"
  },
  {
    "ParameterKey": "BitbucketToken",
    "ParameterValue": "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"
  },
  {
    "ParameterKey": "EndpointType",
    "ParameterValue": "API Gateway"
  },
  {
    "ParameterKey": "LBSubnets",
    "ParameterValue": "subnet-02da95f4862c7436b,subnet-0d24defbffbacee48"
  },
  {
    "ParameterKey": "LBSSLCertificateArn",
    "ParameterValue": ""
  },
  {
    "ParameterKey": "LBCIDR",
    "ParameterValue": ""
  },
  {
    "ParameterKey": "LambdaSubnets",
    "ParameterValue": "subnet-02da95f4862c7436b,subnet-0d24defbffbacee48"
  },
  {
    "ParameterKey": "S3BucketCodePipelineName",
    "ParameterValue": "awscpbitbucketintegrationbssss"
  },
  {
    "ParameterKey": "VPCID",
    "ParameterValue": "vpc-0088b2afbc13a5400"
  },
  {
    "ParameterKey": "WebProxyHost",
    "ParameterValue": ""
  },
  {
    "ParameterKey": "WebProxyPort",
    "ParameterValue": ""
  }
]
